{
    "nodes": [
        {
            "endtime": 600.0,
            "starttime": 0.0,
            "ram": 2048,
            "pes": 2,
            "name": "web0",
            "bw": 1000000000,
            "mips": 8000,
            "type": "vm",
            "size": 1000000
        },
        {
            "endtime": 600.0,
            "starttime": 0.1,
            "ram": 2048,
            "pes": 2,
            "name": "web1",
            "bw": 1000000000,
            "mips": 8000,
            "type": "vm",
            "size": 1000000
        },
        {
            "endtime": 600.0,
            "starttime": 0.2,
            "ram": 2048,
            "pes": 2,
            "name": "web2",
            "bw": 1000000000,
            "mips": 8000,
            "type": "vm",
            "size": 1000000
        },
        {
            "endtime": 600.0,
            "starttime": 0.3,
            "ram": 2048,
            "pes": 2,
            "name": "web3",
            "bw": 1000000000,
            "mips": 8000,
            "type": "vm",
            "size": 1000000
        },
        {
            "endtime": 600.0,
            "starttime": 0.4,
            "ram": 2048,
            "pes": 2,
            "name": "web4",
            "bw": 1000000000,
            "mips": 8000,
            "type": "vm",
            "size": 1000000
        },
        {
            "endtime": 600.0,
            "starttime": 0.5,
            "ram": 2048,
            "pes": 2,
            "name": "web5",
            "bw": 1000000000,
            "mips": 8000,
            "type": "vm",
            "size": 1000000
        },
        {
            "endtime": 600.0,
            "starttime": 0.6,
            "ram": 2048,
            "pes": 2,
            "name": "web6",
            "bw": 1000000000,
            "mips": 8000,
            "type": "vm",
            "size": 1000000
        },
        {
            "endtime": 600.0,
            "starttime": 0.7,
            "ram": 2048,
            "pes": 2,
            "name": "web7",
            "bw": 1000000000,
            "mips": 8000,
            "type": "vm",
            "size": 1000000
        },
        {
            "endtime": 600.0,
            "starttime": 0.8,
            "ram": 2048,
            "pes": 2,
            "name": "web8",
            "bw": 1000000000,
            "mips": 8000,
            "type": "vm",
            "size": 1000000
        },
        {
            "endtime": 600.0,
            "starttime": 0.9,
            "ram": 2048,
            "pes": 2,
            "name": "web9",
            "bw": 1000000000,
            "mips": 8000,
            "type": "vm",
            "size": 1000000
        },
        {
            "endtime": 600.0,
            "starttime": 1.0,
            "ram": 2048,
            "pes": 2,
            "name": "app0",
            "bw": 2000000000,
            "mips": 8000,
            "type": "vm",
            "size": 1000000
        },
        {
            "endtime": 600.0,
            "starttime": 1.1,
            "ram": 2048,
            "pes": 2,
            "name": "app1",
            "bw": 2000000000,
            "mips": 8000,
            "type": "vm",
            "size": 1000000
        },
        {
            "endtime": 600.0,
            "starttime": 1.2,
            "ram": 2048,
            "pes": 2,
            "name": "app2",
            "bw": 2000000000,
            "mips": 8000,
            "type": "vm",
            "size": 1000000
        },
        {
            "endtime": 600.0,
            "starttime": 1.3,
            "ram": 2048,
            "pes": 2,
            "name": "app3",
            "bw": 2000000000,
            "mips": 8000,
            "type": "vm",
            "size": 1000000
        },
        {
            "endtime": 600.0,
            "starttime": 1.4,
            "ram": 2048,
            "pes": 2,
            "name": "app4",
            "bw": 2000000000,
            "mips": 8000,
            "type": "vm",
            "size": 1000000
        },
        {
            "endtime": 600.0,
            "starttime": 1.5,
            "ram": 2048,
            "pes": 2,
            "name": "app5",
            "bw": 2000000000,
            "mips": 8000,
            "type": "vm",
            "size": 1000000
        },
        {
            "endtime": 600.0,
            "starttime": 1.6,
            "ram": 2048,
            "pes": 2,
            "name": "app6",
            "bw": 2000000000,
            "mips": 8000,
            "type": "vm",
            "size": 1000000
        },
        {
            "endtime": 600.0,
            "starttime": 1.7,
            "ram": 2048,
            "pes": 2,
            "name": "app7",
            "bw": 2000000000,
            "mips": 8000,
            "type": "vm",
            "size": 1000000
        },
        {
            "endtime": 600.0,
            "starttime": 1.8,
            "ram": 2048,
            "pes": 2,
            "name": "app8",
            "bw": 2000000000,
            "mips": 8000,
            "type": "vm",
            "size": 1000000
        },
        {
            "endtime": 600.0,
            "starttime": 1.9,
            "ram": 2048,
            "pes": 2,
            "name": "app9",
            "bw": 2000000000,
            "mips": 8000,
            "type": "vm",
            "size": 1000000
        },
        {
            "endtime": 600.0,
            "starttime": 2.0,
            "ram": 4096,
            "pes": 4,
            "name": "db0",
            "bw": 4000000000,
            "mips": 16000,
            "type": "vm",
            "size": 1000000
        },
        {
            "endtime": 600.0,
            "starttime": 2.1,
            "ram": 4096,
            "pes": 4,
            "name": "db1",
            "bw": 4000000000,
            "mips": 16000,
            "type": "vm",
            "size": 1000000
        },
        {
            "endtime": 600.0,
            "starttime": 2.2,
            "ram": 4096,
            "pes": 4,
            "name": "db2",
            "bw": 4000000000,
            "mips": 16000,
            "type": "vm",
            "size": 1000000
        },
        {
            "endtime": 600.0,
            "starttime": 2.3,
            "ram": 4096,
            "pes": 4,
            "name": "db3",
            "bw": 4000000000,
            "mips": 16000,
            "type": "vm",
            "size": 1000000
        },
        {
            "endtime": 600.0,
            "starttime": 2.4,
            "ram": 4096,
            "pes": 4,
            "name": "db4",
            "bw": 4000000000,
            "mips": 16000,
            "type": "vm",
            "size": 1000000
        },
        {
            "endtime": 600.0,
            "starttime": 2.5,
            "ram": 4096,
            "pes": 4,
            "name": "db5",
            "bw": 4000000000,
            "mips": 16000,
            "type": "vm",
            "size": 1000000
        },
        {
            "endtime": 600.0,
            "starttime": 2.6,
            "ram": 4096,
            "pes": 4,
            "name": "db6",
            "bw": 4000000000,
            "mips": 16000,
            "type": "vm",
            "size": 1000000
        },
        {
            "endtime": 600.0,
            "starttime": 2.7,
            "ram": 4096,
            "pes": 4,
            "name": "db7",
            "bw": 4000000000,
            "mips": 16000,
            "type": "vm",
            "size": 1000000
        },
        {
            "endtime": 600.0,
            "starttime": 2.8,
            "ram": 4096,
            "pes": 4,
            "name": "db8",
            "bw": 4000000000,
            "mips": 16000,
            "type": "vm",
            "size": 1000000
        },
        {
            "endtime": 600.0,
            "starttime": 2.9,
            "ram": 4096,
            "pes": 4,
            "name": "db9",
            "bw": 4000000000,
            "mips": 16000,
            "type": "vm",
            "size": 1000000
        },
        {
            "endtime": 600.0,
            "starttime": 3.0,
            "ram": 2048,
            "pes": 2,
            "name": "svc0",
            "bw": 2000000000,
            "mips": 8000,
            "type": "vm",
            "size": 1000000
        },
        {
            "endtime": 600.0,
            "starttime": 3.1,
            "ram": 2048,
            "pes": 2,
            "name": "svc1",
            "bw": 2000000000,
            "mips": 8000,
            "type": "vm",
            "size": 1000000
        },
        {
            "endtime": 600.0,
            "starttime": 3.2,
            "ram": 2048,
            "pes": 2,
            "name": "svc2",
            "bw": 2000000000,
            "mips": 8000,
            "type": "vm",
            "size": 1000000
        },
        {
            "endtime": 600.0,
            "starttime": 3.3,
            "ram": 2048,
            "pes": 2,
            "name": "svc3",
            "bw": 2000000000,
            "mips": 8000,
            "type": "vm",
            "size": 1000000
        },
        {
            "endtime": 600.0,
            "starttime": 3.4,
            "ram": 2048,
            "pes": 2,
            "name": "svc4",
            "bw": 2000000000,
            "mips": 8000,
            "type": "vm",
            "size": 1000000
        },
        {
            "endtime": 600.0,
            "starttime": 3.5,
            "ram": 2048,
            "pes": 2,
            "name": "svc5",
            "bw": 2000000000,
            "mips": 8000,
            "type": "vm",
            "size": 1000000
        },
        {
            "endtime": 600.0,
            "starttime": 3.6,
            "ram": 2048,
            "pes": 2,
            "name": "svc6",
            "bw": 2000000000,
            "mips": 8000,
            "type": "vm",
            "size": 1000000
        },
        {
            "endtime": 600.0,
            "starttime": 3.7,
            "ram": 2048,
            "pes": 2,
            "name": "svc7",
            "bw": 2000000000,
            "mips": 8000,
            "type": "vm",
            "size": 1000000
        },
        {
            "endtime": 600.0,
            "starttime": 3.8,
            "ram": 2048,
            "pes": 2,
            "name": "svc8",
            "bw": 2000000000,
            "mips": 8000,
            "type": "vm",
            "size": 1000000
        },
        {
            "endtime": 600.0,
            "starttime": 3.9,
            "ram": 2048,
            "pes": 2,
            "name": "svc9",
            "bw": 2000000000,
            "mips": 8000,
            "type": "vm",
            "size": 1000000
        }
    ],
    "links": [
        {
            "source": "web0",
            "name": "l_web0_app0",
            "bandwidth": 1000000000,
            "destination": "app0"
        },
        {
            "source": "web0",
            "name": "l_web0_app1",
            "bandwidth": 1000000000,
            "destination": "app1"
        },
        {
            "source": "web1",
            "name": "l_web1_app1",
            "bandwidth": 1000000000,
            "destination": "app1"
        },
        {
            "source": "web1",
            "name": "l_web1_app2",
            "bandwidth": 1000000000,
            "destination": "app2"
        },
        {
            "source": "web2",
            "name": "l_web2_app2",
            "bandwidth": 1000000000,
            "destination": "app2"
        },
        {
            "source": "web2",
            "name": "l_web2_app3",
            "bandwidth": 1000000000,
            "destination": "app3"
        },
        {
            "source": "web3",
            "name": "l_web3_app3",
            "bandwidth": 1000000000,
            "destination": "app3"
        },
        {
            "source": "web3",
            "name": "l_web3_app4",
            "bandwidth": 1000000000,
            "destination": "app4"
        },
        {
            "source": "web4",
            "name": "l_web4_app4",
            "bandwidth": 1000000000,
            "destination": "app4"
        },
        {
            "source": "web4",
            "name": "l_web4_app5",
            "bandwidth": 1000000000,
            "destination": "app5"
        },
        {
            "source": "web5",
            "name": "l_web5_app5",
            "bandwidth": 1000000000,
            "destination": "app5"
        },
        {
            "source": "web5",
            "name": "l_web5_app6",
            "bandwidth": 1000000000,
            "destination": "app6"
        },
        {
            "source": "web6",
            "name": "l_web6_app6",
            "bandwidth": 1000000000,
            "destination": "app6"
        },
        {
            "source": "web6",
            "name": "l_web6_app7",
            "bandwidth": 1000000000,
            "destination": "app7"
        },
        {
            "source": "web7",
            "name": "l_web7_app7",
            "bandwidth": 1000000000,
            "destination": "app7"
        },
        {
            "source": "web7",
            "name": "l_web7_app8",
            "bandwidth": 1000000000,
            "destination": "app8"
        },
        {
            "source": "web8",
            "name": "l_web8_app8",
            "bandwidth": 1000000000,
            "destination": "app8"
        },
        {
            "source": "web8",
            "name": "l_web8_app9",
            "bandwidth": 1000000000,
            "destination": "app9"
        },
        {
            "source": "web9",
            "name": "l_web9_app9",
            "bandwidth": 1000000000,
            "destination": "app9"
        },
        {
            "source": "web9",
            "name": "l_web9_app0",
            "bandwidth": 1000000000,
            "destination": "app0"
        },
        {
            "source": "app0",
            "name": "l_app0_db0",
            "bandwidth": 2000000000,
            "destination": "db0"
        },
        {
            "source": "app0",
            "name": "l_app0_db1",
            "bandwidth": 2000000000,
            "destination": "db1"
        },
        {
            "source": "app1",
            "name": "l_app1_db1",
            "bandwidth": 2000000000,
            "destination": "db1"
        },
        {
            "source": "app1",
            "name": "l_app1_db2",
            "bandwidth": 2000000000,
            "destination": "db2"
        },
        {
            "source": "app2",
            "name": "l_app2_db2",
            "bandwidth": 2000000000,
            "destination": "db2"
        },
        {
            "source": "app2",
            "name": "l_app2_db3",
            "bandwidth": 2000000000,
            "destination": "db3"
        },
        {
            "source": "app3",
            "name": "l_app3_db3",
            "bandwidth": 2000000000,
            "destination": "db3"
        },
        {
            "source": "app3",
            "name": "l_app3_db4",
            "bandwidth": 2000000000,
            "destination": "db4"
        },
        {
            "source": "app4",
            "name": "l_app4_db4",
            "bandwidth": 2000000000,
            "destination": "db4"
        },
        {
            "source": "app4",
            "name": "l_app4_db5",
            "bandwidth": 2000000000,
            "destination": "db5"
        },
        {
            "source": "app5",
            "name": "l_app5_db5",
            "bandwidth": 2000000000,
            "destination": "db5"
        },
        {
            "source": "app5",
            "name": "l_app5_db6",
            "bandwidth": 2000000000,
            "destination": "db6"
        },
        {
            "source": "app6",
            "name": "l_app6_db6",
            "bandwidth": 2000000000,
            "destination": "db6"
        },
        {
            "source": "app6",
            "name": "l_app6_db7",
            "bandwidth": 2000000000,
            "destination": "db7"
        },
        {
            "source": "app7",
            "name": "l_app7_db7",
            "bandwidth": 2000000000,
            "destination": "db7"
        },
        {
            "source": "app7",
            "name": "l_app7_db8",
            "bandwidth": 2000000000,
            "destination": "db8"
        },
        {
            "source": "app8",
            "name": "l_app8_db8",
            "bandwidth": 2000000000,
            "destination": "db8"
        },
        {
            "source": "app8",
            "name": "l_app8_db9",
            "bandwidth": 2000000000,
            "destination": "db9"
        },
        {
            "source": "app9",
            "name": "l_app9_db9",
            "bandwidth": 2000000000,
            "destination": "db9"
        },
        {
            "source": "app9",
            "name": "l_app9_db0",
            "bandwidth": 2000000000,
            "destination": "db0"
        },
        {
            "source": "db0",
            "name": "l_db0_app0",
            "bandwidth": 2000000000,
            "destination": "app0"
        },
        {
            "source": "db0",
            "name": "l_db0_app1",
            "bandwidth": 2000000000,
            "destination": "app1"
        },
        {
            "source": "db1",
            "name": "l_db1_app1",
            "bandwidth": 2000000000,
            "destination": "app1"
        },
        {
            "source": "db1",
            "name": "l_db1_app2",
            "bandwidth": 2000000000,
            "destination": "app2"
        },
        {
            "source": "db2",
            "name": "l_db2_app2",
            "bandwidth": 2000000000,
            "destination": "app2"
        },
        {
            "source": "db2",
            "name": "l_db2_app3",
            "bandwidth": 2000000000,
            "destination": "app3"
        },
        {
            "source": "db3",
            "name": "l_db3_app3",
            "bandwidth": 2000000000,
            "destination": "app3"
        },
        {
            "source": "db3",
            "name": "l_db3_app4",
            "bandwidth": 2000000000,
            "destination": "app4"
        },
        {
            "source": "db4",
            "name": "l_db4_app4",
            "bandwidth": 2000000000,
            "destination": "app4"
        },
        {
            "source": "db4",
            "name": "l_db4_app5",
            "bandwidth": 2000000000,
            "destination": "app5"
        },
        {
            "source": "db5",
            "name": "l_db5_app5",
            "bandwidth": 2000000000,
            "destination": "app5"
        },
        {
            "source": "db5",
            "name": "l_db5_app6",
            "bandwidth": 2000000000,
            "destination": "app6"
        },
        {
            "source": "db6",
            "name": "l_db6_app6",
            "bandwidth": 2000000000,
            "destination": "app6"
        },
        {
            "source": "db6",
            "name": "l_db6_app7",
            "bandwidth": 2000000000,
            "destination": "app7"
        },
        {
            "source": "db7",
            "name": "l_db7_app7",
            "bandwidth": 2000000000,
            "destination": "app7"
        },
        {
            "source": "db7",
            "name": "l_db7_app8",
            "bandwidth": 2000000000,
            "destination": "app8"
        },
        {
            "source": "db8",
            "name": "l_db8_app8",
            "bandwidth": 2000000000,
            "destination": "app8"
        },
        {
            "source": "db8",
            "name": "l_db8_app9",
            "bandwidth": 2000000000,
            "destination": "app9"
        },
        {
            "source": "db9",
            "name": "l_db9_app9",
            "bandwidth": 2000000000,
            "destination": "app9"
        },
        {
            "source": "db9",
            "name": "l_db9_app0",
            "bandwidth": 2000000000,
            "destination": "app0"
        },
        {
            "source": "app0",
            "name": "l_app0_web0",
            "bandwidth": 1000000000,
            "destination": "web0"
        },
        {
            "source": "app0",
            "name": "l_app0_web1",
            "bandwidth": 1000000000,
            "destination": "web1"
        },
        {
            "source": "app1",
            "name": "l_app1_web1",
            "bandwidth": 1000000000,
            "destination": "web1"
        },
        {
            "source": "app1",
            "name": "l_app1_web2",
            "bandwidth": 1000000000,
            "destination": "web2"
        },
        {
            "source": "app2",
            "name": "l_app2_web2",
            "bandwidth": 1000000000,
            "destination": "web2"
        },
        {
            "source": "app2",
            "name": "l_app2_web3",
            "bandwidth": 1000000000,
            "destination": "web3"
        },
        {
            "source": "app3",
            "name": "l_app3_web3",
            "bandwidth": 1000000000,
            "destination": "web3"
        },
        {
            "source": "app3",
            "name": "l_app3_web4",
            "bandwidth": 1000000000,
            "destination": "web4"
        },
        {
            "source": "app4",
            "name": "l_app4_web4",
            "bandwidth": 1000000000,
            "destination": "web4"
        },
        {
            "source": "app4",
            "name": "l_app4_web5",
            "bandwidth": 1000000000,
            "destination": "web5"
        },
        {
            "source": "app5",
            "name": "l_app5_web5",
            "bandwidth": 1000000000,
            "destination": "web5"
        },
        {
            "source": "app5",
            "name": "l_app5_web6",
            "bandwidth": 1000000000,
            "destination": "web6"
        },
        {
            "source": "app6",
            "name": "l_app6_web6",
            "bandwidth": 1000000000,
            "destination": "web6"
        },
        {
            "source": "app6",
            "name": "l_app6_web7",
            "bandwidth": 1000000000,
            "destination": "web7"
        },
        {
            "source": "app7",
            "name": "l_app7_web7",
            "bandwidth": 1000000000,
            "destination": "web7"
        },
        {
            "source": "app7",
            "name": "l_app7_web8",
            "bandwidth": 1000000000,
            "destination": "web8"
        },
        {
            "source": "app8",
            "name": "l_app8_web8",
            "bandwidth": 1000000000,
            "destination": "web8"
        },
        {
            "source": "app8",
            "name": "l_app8_web9",
            "bandwidth": 1000000000,
            "destination": "web9"
        },
        {
            "source": "app9",
            "name": "l_app9_web9",
            "bandwidth": 1000000000,
            "destination": "web9"
        },
        {
            "source": "app9",
            "name": "l_app9_web0",
            "bandwidth": 1000000000,
            "destination": "web0"
        },
        {
            "source": "app0",
            "name": "l_app0_svc0",
            "bandwidth": 1000000000,
            "destination": "svc0"
        },
        {
            "source": "app1",
            "name": "l_app1_svc1",
            "bandwidth": 1000000000,
            "destination": "svc1"
        },
        {
            "source": "app2",
            "name": "l_app2_svc2",
            "bandwidth": 1000000000,
            "destination": "svc2"
        },
        {
            "source": "app3",
            "name": "l_app3_svc3",
            "bandwidth": 1000000000,
            "destination": "svc3"
        },
        {
            "source": "app4",
            "name": "l_app4_svc4",
            "bandwidth": 1000000000,
            "destination": "svc4"
        },
        {
            "source": "app5",
            "name": "l_app5_svc5",
            "bandwidth": 1000000000,
            "destination": "svc5"
        },
        {
            "source": "app6",
            "name": "l_app6_svc6",
            "bandwidth": 1000000000,
            "destination": "svc6"
        },
        {
            "source": "app7",
            "name": "l_app7_svc7",
            "bandwidth": 1000000000,
            "destination": "svc7"
        },
        {
            "source": "app8",
            "name": "l_app8_svc8",
            "bandwidth": 1000000000,
            "destination": "svc8"
        },
        {
            "source": "app9",
            "name": "l_app9_svc9",
            "bandwidth": 1000000000,
            "destination": "svc9"
        },
        {
            "source": "svc0",
            "name": "l_svc0_app0",
            "bandwidth": 1000000000,
            "destination": "app0"
        },
        {
            "source": "svc1",
            "name": "l_svc1_app1",
            "bandwidth": 1000000000,
            "destination": "app1"
        },
        {
            "source": "svc2",
            "name": "l_svc2_app2",
            "bandwidth": 1000000000,
            "destination": "app2"
        },
        {
            "source": "svc3",
            "name": "l_svc3_app3",
            "bandwidth": 1000000000,
            "destination": "app3"
        },
        {
            "source": "svc4",
            "name": "l_svc4_app4",
            "bandwidth": 1000000000,
            "destination": "app4"
        },
        {
            "source": "svc5",
            "name": "l_svc5_app5",
            "bandwidth": 1000000000,
            "destination": "app5"
        },
        {
            "source": "svc6",
            "name": "l_svc6_app6",
            "bandwidth": 1000000000,
            "destination": "app6"
        },
        {
            "source": "svc7",
            "name": "l_svc7_app7",
            "bandwidth": 1000000000,
            "destination": "app7"
        },
        {
            "source": "svc8",
            "name": "l_svc8_app8",
            "bandwidth": 1000000000,
            "destination": "app8"
        },
        {
            "source": "svc9",
            "name": "l_svc9_app9",
            "bandwidth": 1000000000,
            "destination": "app9"
        }
    ]
}